{
    "number": 25,
    "year": 2021,
    "days": [
        {
            "date": "2021-06-21",
            "dishes": [
                {
                    "name": "Kalte Gurkensuppe",
                    "prices": {
                        "students": {
                            "base_price": "N/A",
                            "price_per_unit": null,
                            "unit": null
                        },
                        "staff": {
                            "base_price": "N/A",
                            "price_per_unit": null,
                            "unit": null
                        },
                        "guests": {
                            "base_price": "N/A",
                            "price_per_unit": null,
                            "unit": null
                        }
                    },
                    "ingredients": [
                        "Mi"
                    ],
                    "dish_type": "Suppe"
                },
                {
                    "name": "Brokkoli Wok mit Tofu",
                    "prices": {
                        "students": {
                            "base_price": "N/A",
                            "price_per_unit": null,
                            "unit": null
                        },
                        "staff": {
                            "base_price": "N/A",
                            "price_per_unit": null,
                            "unit": null
                        },
                        "guests": {
                            "base_price": "N/A",
                            "price_per_unit": null,
                            "unit": null
                        }
                    },
                    "ingredients": [
                        "So"
                    ],
                    "dish_type": "Hauptkomponente"
                },
                {
                    "name": "Vegetarische Frühlingrollen",
                    "prices": {
                        "students": {
                            "base_price": "N/A",
                            "price_per_unit": null,
                            "unit": null
                        },
                        "staff": {
                            "base_price": "N/A",
                            "price_per_unit": null,
                            "unit": null
                        },
                        "guests": {
                            "base_price": "N/A",
                            "price_per_unit": null,
                            "unit": null
                        }
                    },
                    "ingredients": [
                        "Ei",
                        "Gl",
                        "Se",
                        "So"
                    ],
                    "dish_type": "Hauptkomponente"
                },
                {
                    "name": "Grüne Tagliatelle in Sahnesoße mit Räucherlachs und Blattsalat mit Radicchio",
                    "prices": {
                        "students": {
                            "base_price": 3.05,
                            "price_per_unit": null,
                            "unit": null
                        },
                        "staff": {
                            "base_price": 3.05,
                            "price_per_unit": null,
                            "unit": null
                        },
                        "guests": {
                            "base_price": 3.05,
                            "price_per_unit": null,
                            "unit": null
                        }
                    },
                    "ingredients": [
                        "9",
                        "Ei",
                        "Fi",
                        "Gl",
                        "Mi",
                        "Sf",
                        "Sw"
                    ],
                    "dish_type": "Extraessen"
                }
            ]
        },
        {
            "date": "2021-06-22",
            "dishes": [
                {
                    "name": "Tomatensuppe",
                    "prices": {
                        "students": {
                            "base_price": "N/A",
                            "price_per_unit": null,
                            "unit": null
                        },
                        "staff": {
                            "base_price": "N/A",
                            "price_per_unit": null,
                            "unit": null
                        },
                        "guests": {
                            "base_price": "N/A",
                            "price_per_unit": null,
                            "unit": null
                        }
                    },
                    "ingredients": [
                        "Gl",
                        "Mi"
                    ],
                    "dish_type": "Suppe"
                },
                {
                    "name": "Salatteller mit Putenstreifen",
                    "prices": {
                        "students": {
                            "base_price": "N/A",
                            "price_per_unit": null,
                            "unit": null
                        },
                        "staff": {
                            "base_price": "N/A",
                            "price_per_unit": null,
                            "unit": null
                        },
                        "guests": {
                            "base_price": "N/A",
                            "price_per_unit": null,
                            "unit": null
                        }
                    },
                    "ingredients": [
                        "G"
                    ],
                    "dish_type": "Hauptkomponente"
                },
                {
                    "name": "Grünes Kokos-Curry mit Erdnussreis",
                    "prices": {
                        "students": {
                            "base_price": "N/A",
                            "price_per_unit": null,
                            "unit": null
                        },
                        "staff": {
                            "base_price": "N/A",
                            "price_per_unit": null,
                            "unit": null
                        },
                        "guests": {
                            "base_price": "N/A",
                            "price_per_unit": null,
                            "unit": null
                        }
                    },
                    "ingredients": [
                        "En",
                        "Gl",
                        "Mi",
                        "So"
                    ],
                    "dish_type": "Hauptkomponente"
                },
                {
                    "name": "Gegrilltes halbes Hendl mit Brezn und Rucola-Radicchio-Salat",
                    "prices": {
                        "students": {
                            "base_price": 4.85,
                            "price_per_unit": null,
                            "unit": null
                        },
                        "staff": {
                            "base_price": 4.85,
                            "price_per_unit": null,
                            "unit": null
                        },
                        "guests": {
                            "base_price": 4.85,
                            "price_per_unit": null,
                            "unit": null
                        }
                    },
                    "ingredients": [
                        "9",
                        "G",
                        "Gl",
                        "Mi",
                        "Sf",
                        "So",
                        "Sw"
                    ],
                    "dish_type": "Extraessen"
                }
            ]
        },
        {
            "date": "2021-06-23",
            "dishes": [
                {
                    "name": "Klare Zwiebelsuppe",
                    "prices": {
                        "students": {
                            "base_price": "N/A",
                            "price_per_unit": null,
                            "unit": null
                        },
                        "staff": {
                            "base_price": "N/A",
                            "price_per_unit": null,
                            "unit": null
                        },
                        "guests": {
                            "base_price": "N/A",
                            "price_per_unit": null,
                            "unit": null
                        }
                    },
                    "ingredients": [],
                    "dish_type": "Suppe"
                },
                {
                    "name": "Gefüllte Paprikaschote",
                    "prices": {
                        "students": {
                            "base_price": "N/A",
                            "price_per_unit": null,
                            "unit": null
                        },
                        "staff": {
                            "base_price": "N/A",
                            "price_per_unit": null,
                            "unit": null
                        },
                        "guests": {
                            "base_price": "N/A",
                            "price_per_unit": null,
                            "unit": null
                        }
                    },
                    "ingredients": [
                        "Ei",
                        "R",
                        "S"
                    ],
                    "dish_type": "Hauptkomponente"
                },
                {
                    "name": "Spiegelei mit Rote-Bete-Kartoffel-Gemüse",
                    "prices": {
                        "students": {
                            "base_price": "N/A",
                            "price_per_unit": null,
                            "unit": null
                        },
                        "staff": {
                            "base_price": "N/A",
                            "price_per_unit": null,
                            "unit": null
                        },
                        "guests": {
                            "base_price": "N/A",
                            "price_per_unit": null,
                            "unit": null
                        }
                    },
                    "ingredients": [
                        "Ei"
                    ],
                    "dish_type": "Hauptkomponente"
                },
                {
                    "name": "Reispfanne mit Karotten, Sellerie und Romanesco, Sauerrahmdip mit Koriander",
                    "prices": {
                        "students": {
                            "base_price": 2.3,
                            "price_per_unit": null,
                            "unit": null
                        },
                        "staff": {
                            "base_price": 2.3,
                            "price_per_unit": null,
                            "unit": null
                        },
                        "guests": {
                            "base_price": 2.3,
                            "price_per_unit": null,
                            "unit": null
                        }
                    },
                    "ingredients": [
                        "Mi",
                        "Sl"
                    ],
                    "dish_type": "Extraessen"
                }
            ]
        },
        {
            "date": "2021-06-24",
            "dishes": [
                {
                    "name": "Kräuterrahmsuppe",
                    "prices": {
                        "students": {
                            "base_price": "N/A",
                            "price_per_unit": null,
                            "unit": null
                        },
                        "staff": {
                            "base_price": "N/A",
                            "price_per_unit": null,
                            "unit": null
                        },
                        "guests": {
                            "base_price": "N/A",
                            "price_per_unit": null,
                            "unit": null
                        }
                    },
                    "ingredients": [
                        "Gl",
                        "Mi"
                    ],
                    "dish_type": "Suppe"
                },
                {
                    "name": "Rinderhackbraten",
                    "prices": {
                        "students": {
                            "base_price": "N/A",
                            "price_per_unit": null,
                            "unit": null
                        },
                        "staff": {
                            "base_price": "N/A",
                            "price_per_unit": null,
                            "unit": null
                        },
                        "guests": {
                            "base_price": "N/A",
                            "price_per_unit": null,
                            "unit": null
                        }
                    },
                    "ingredients": [
                        "Ei",
                        "Gl",
                        "Mi",
                        "R",
                        "So"
                    ],
                    "dish_type": "Hauptkomponente"
                },
                {
                    "name": "Vollkornnudeln mit Champignon-Tomaten-Soße",
                    "prices": {
                        "students": {
                            "base_price": "N/A",
                            "price_per_unit": null,
                            "unit": null
                        },
                        "staff": {
                            "base_price": "N/A",
                            "price_per_unit": null,
                            "unit": null
                        },
                        "guests": {
                            "base_price": "N/A",
                            "price_per_unit": null,
                            "unit": null
                        }
                    },
                    "ingredients": [
                        "Ei",
                        "Gl",
                        "Mi"
                    ],
                    "dish_type": "Hauptkomponente"
                },
                {
                    "name": "Kichererbsen-Auberginen-Pfanne mit Minzjoghurt",
                    "prices": {
                        "students": {
                            "base_price": 1.95,
                            "price_per_unit": null,
                            "unit": null
                        },
                        "staff": {
                            "base_price": 1.95,
                            "price_per_unit": null,
                            "unit": null
                        },
                        "guests": {
                            "base_price": 1.95,
                            "price_per_unit": null,
                            "unit": null
                        }
                    },
                    "ingredients": [
                        "Mi"
                    ],
                    "dish_type": "Extraessen"
                }
            ]
        },
        {
            "date": "2021-06-25",
            "dishes": [
                {
                    "name": "Kohlrabicremesuppe",
                    "prices": {
                        "students": {
                            "base_price": "N/A",
                            "price_per_unit": null,
                            "unit": null
                        },
                        "staff": {
                            "base_price": "N/A",
                            "price_per_unit": null,
                            "unit": null
                        },
                        "guests": {
                            "base_price": "N/A",
                            "price_per_unit": null,
                            "unit": null
                        }
                    },
                    "ingredients": [
                        "Gl",
                        "Mi"
                    ],
                    "dish_type": "Suppe"
                },
                {
                    "name": "Seelachsfilet auf serbische Art",
                    "prices": {
                        "students": {
                            "base_price": "N/A",
                            "price_per_unit": null,
                            "unit": null
                        },
                        "staff": {
                            "base_price": "N/A",
                            "price_per_unit": null,
                            "unit": null
                        },
                        "guests": {
                            "base_price": "N/A",
                            "price_per_unit": null,
                            "unit": null
                        }
                    },
                    "ingredients": [
                        "1",
                        "2",
                        "Ei",
                        "Fi",
                        "Gl",
                        "Mi",
                        "So"
                    ],
                    "dish_type": "Hauptkomponente"
                },
                {
                    "name": "Farfalle mit Feta",
                    "prices": {
                        "students": {
                            "base_price": "N/A",
                            "price_per_unit": null,
                            "unit": null
                        },
                        "staff": {
                            "base_price": "N/A",
                            "price_per_unit": null,
                            "unit": null
                        },
                        "guests": {
                            "base_price": "N/A",
                            "price_per_unit": null,
                            "unit": null
                        }
                    },
                    "ingredients": [
                        "Ei",
                        "Gl",
                        "Mi"
                    ],
                    "dish_type": "Hauptkomponente"
                },
                {
                    "name": "Kartoffel-Kräuterküchlein mit Mandel-Brokkoli und Paprikadip",
                    "prices": {
                        "students": {
                            "base_price": 1.9,
                            "price_per_unit": null,
                            "unit": null
                        },
                        "staff": {
                            "base_price": 1.9,
                            "price_per_unit": null,
                            "unit": null
                        },
                        "guests": {
                            "base_price": 1.9,
                            "price_per_unit": null,
                            "unit": null
                        }
                    },
                    "ingredients": [
                        "2",
                        "3",
                        "5",
                        "Ei",
                        "Mi",
                        "Sc",
                        "Sw"
                    ],
                    "dish_type": "Extraessen"
                }
            ]
        },
        {
            "date": "2021-06-26",
            "dishes": [
                {
                    "name": "Karotten-IngwerSuppe",
                    "prices": {
                        "students": {
                            "base_price": "N/A",
                            "price_per_unit": null,
                            "unit": null
                        },
                        "staff": {
                            "base_price": "N/A",
                            "price_per_unit": null,
                            "unit": null
                        },
                        "guests": {
                            "base_price": "N/A",
                            "price_per_unit": null,
                            "unit": null
                        }
                    },
                    "ingredients": [
                        "Gl",
                        "Mi"
                    ],
                    "dish_type": "Suppe"
                },
                {
                    "name": "Putenragout",
                    "prices": {
                        "students": {
                            "base_price": "N/A",
                            "price_per_unit": null,
                            "unit": null
                        },
                        "staff": {
                            "base_price": "N/A",
                            "price_per_unit": null,
                            "unit": null
                        },
                        "guests": {
                            "base_price": "N/A",
                            "price_per_unit": null,
                            "unit": null
                        }
                    },
                    "ingredients": [
                        "G",
                        "Gl",
                        "Mi"
                    ],
                    "dish_type": "Hauptkomponente"
                },
                {
                    "name": "Möhren-Zucchini-Risotto",
                    "prices": {
                        "students": {
                            "base_price": "N/A",
                            "price_per_unit": null,
                            "unit": null
                        },
                        "staff": {
                            "base_price": "N/A",
                            "price_per_unit": null,
                            "unit": null
                        },
                        "guests": {
                            "base_price": "N/A",
                            "price_per_unit": null,
                            "unit": null
                        }
                    },
                    "ingredients": [
                        "1",
                        "2",
                        "Mi",
                        "Sw"
                    ],
                    "dish_type": "Hauptkomponente"
                }
            ]
        },
        {
            "date": "2021-06-27",
            "dishes": [
                {
                    "name": "Brühe mit Maultaschen",
                    "prices": {
                        "students": {
                            "base_price": "N/A",
                            "price_per_unit": null,
                            "unit": null
                        },
                        "staff": {
                            "base_price": "N/A",
                            "price_per_unit": null,
                            "unit": null
                        },
                        "guests": {
                            "base_price": "N/A",
                            "price_per_unit": null,
                            "unit": null
                        }
                    },
                    "ingredients": [
                        "Ei",
                        "Gl",
                        "R",
                        "Sl",
                        "So"
                    ],
                    "dish_type": "Suppe"
                },
                {
                    "name": "Rinderbraten",
                    "prices": {
                        "students": {
                            "base_price": "N/A",
                            "price_per_unit": null,
                            "unit": null
                        },
                        "staff": {
                            "base_price": "N/A",
                            "price_per_unit": null,
                            "unit": null
                        },
                        "guests": {
                            "base_price": "N/A",
                            "price_per_unit": null,
                            "unit": null
                        }
                    },
                    "ingredients": [
                        "Gl",
                        "Mi",
                        "R",
                        "Sl"
                    ],
                    "dish_type": "Hauptkomponente"
                },
                {
                    "name": "Linsen-Curry mit Mango und Kokos",
                    "prices": {
                        "students": {
                            "base_price": "N/A",
                            "price_per_unit": null,
                            "unit": null
                        },
                        "staff": {
                            "base_price": "N/A",
                            "price_per_unit": null,
                            "unit": null
                        },
                        "guests": {
                            "base_price": "N/A",
                            "price_per_unit": null,
                            "unit": null
                        }
                    },
                    "ingredients": [
                        "Gl",
                        "So"
                    ],
                    "dish_type": "Hauptkomponente"
                }
            ]
        }
    ]
}