{
    "number": 19,
    "year": 2021,
    "days": [
        {
            "date": "2021-05-10",
            "dishes": [
                {
                    "name": "Ravioli mit Pilzfüllung in pikanter Kräutersauce",
                    "prices": {
                        "students": {
                            "base_price": "N/A",
                            "price_per_unit": null,
                            "unit": null
                        },
                        "staff": {
                            "base_price": "N/A",
                            "price_per_unit": null,
                            "unit": null
                        },
                        "guests": {
                            "base_price": "N/A",
                            "price_per_unit": null,
                            "unit": null
                        }
                    },
                    "ingredients": [
                        "Ei",
                        "Gl",
                        "GlW",
                        "Kn",
                        "Mi",
                        "Sl"
                    ],
                    "dish_type": "Pasta"
                },
                {
                    "name": "Kotelett vom Lamm mit Rosmarinjus",
                    "prices": {
                        "students": {
                            "base_price": "N/A",
                            "price_per_unit": null,
                            "unit": null
                        },
                        "staff": {
                            "base_price": "N/A",
                            "price_per_unit": null,
                            "unit": null
                        },
                        "guests": {
                            "base_price": "N/A",
                            "price_per_unit": null,
                            "unit": null
                        }
                    },
                    "ingredients": [
                        "Gl",
                        "GlG",
                        "GlW",
                        "Kn",
                        "Mi"
                    ],
                    "dish_type": "Grill"
                },
                {
                    "name": "Spargel-Pilz-Curry indische Art (weißer Spargel g.g.A.)",
                    "prices": {
                        "students": {
                            "base_price": "N/A",
                            "price_per_unit": null,
                            "unit": null
                        },
                        "staff": {
                            "base_price": "N/A",
                            "price_per_unit": null,
                            "unit": null
                        },
                        "guests": {
                            "base_price": "N/A",
                            "price_per_unit": null,
                            "unit": null
                        }
                    },
                    "ingredients": [
                        "2",
                        "Kn"
                    ],
                    "dish_type": "Wok"
                },
                {
                    "name": "Arabischer Couscous mit Karotten und Kichererbsen",
                    "prices": {
                        "students": {
                            "base_price": "N/A",
                            "price_per_unit": null,
                            "unit": null
                        },
                        "staff": {
                            "base_price": "N/A",
                            "price_per_unit": null,
                            "unit": null
                        },
                        "guests": {
                            "base_price": "N/A",
                            "price_per_unit": null,
                            "unit": null
                        }
                    },
                    "ingredients": [
                        "2",
                        "Gl",
                        "GlW",
                        "Kn"
                    ],
                    "dish_type": "Vegan, Eintopf, Suppe"
                },
                {
                    "name": "Tagessuppe",
                    "prices": {
                        "students": {
                            "base_price": "N/A",
                            "price_per_unit": null,
                            "unit": null
                        },
                        "staff": {
                            "base_price": "N/A",
                            "price_per_unit": null,
                            "unit": null
                        },
                        "guests": {
                            "base_price": "N/A",
                            "price_per_unit": null,
                            "unit": null
                        }
                    },
                    "ingredients": [],
                    "dish_type": ""
                },
                {
                    "name": "Gefüllte Paprikaschote mit Tomatensauce",
                    "prices": {
                        "students": {
                            "base_price": "N/A",
                            "price_per_unit": null,
                            "unit": null
                        },
                        "staff": {
                            "base_price": "N/A",
                            "price_per_unit": null,
                            "unit": null
                        },
                        "guests": {
                            "base_price": "N/A",
                            "price_per_unit": null,
                            "unit": null
                        }
                    },
                    "ingredients": [
                        "2",
                        "Gl",
                        "GlD",
                        "GlW",
                        "Kn",
                        "Mi"
                    ],
                    "dish_type": "Vegetarisch"
                }
            ]
        },
        {
            "date": "2021-05-11",
            "dishes": [
                {
                    "name": "Pasta mit Gorgonzolasauce",
                    "prices": {
                        "students": {
                            "base_price": "N/A",
                            "price_per_unit": null,
                            "unit": null
                        },
                        "staff": {
                            "base_price": "N/A",
                            "price_per_unit": null,
                            "unit": null
                        },
                        "guests": {
                            "base_price": "N/A",
                            "price_per_unit": null,
                            "unit": null
                        }
                    },
                    "ingredients": [
                        "Gl",
                        "GlW",
                        "Mi"
                    ],
                    "dish_type": "Pasta"
                },
                {
                    "name": "Phad Thai mit Spargel (g.g.A.) und Tofuwürfeln",
                    "prices": {
                        "students": {
                            "base_price": "N/A",
                            "price_per_unit": null,
                            "unit": null
                        },
                        "staff": {
                            "base_price": "N/A",
                            "price_per_unit": null,
                            "unit": null
                        },
                        "guests": {
                            "base_price": "N/A",
                            "price_per_unit": null,
                            "unit": null
                        }
                    },
                    "ingredients": [
                        "2",
                        "En",
                        "Fi",
                        "Gl",
                        "GlW",
                        "Kn",
                        "Se",
                        "So"
                    ],
                    "dish_type": "Wok"
                },
                {
                    "name": "Getreidepfanne mit frischem Gemüse",
                    "prices": {
                        "students": {
                            "base_price": "N/A",
                            "price_per_unit": null,
                            "unit": null
                        },
                        "staff": {
                            "base_price": "N/A",
                            "price_per_unit": null,
                            "unit": null
                        },
                        "guests": {
                            "base_price": "N/A",
                            "price_per_unit": null,
                            "unit": null
                        }
                    },
                    "ingredients": [
                        "Gl",
                        "GlW"
                    ],
                    "dish_type": "Vegan, Eintopf, Suppe"
                },
                {
                    "name": "Spargelcremesuppe (g.g.A.) mit Croutons",
                    "prices": {
                        "students": {
                            "base_price": "N/A",
                            "price_per_unit": null,
                            "unit": null
                        },
                        "staff": {
                            "base_price": "N/A",
                            "price_per_unit": null,
                            "unit": null
                        },
                        "guests": {
                            "base_price": "N/A",
                            "price_per_unit": null,
                            "unit": null
                        }
                    },
                    "ingredients": [
                        "Gl",
                        "GlG",
                        "GlR",
                        "GlW",
                        "Mi"
                    ],
                    "dish_type": ""
                },
                {
                    "name": "Quiche mit grünem und weißem (g.g.A.) Spargel",
                    "prices": {
                        "students": {
                            "base_price": "N/A",
                            "price_per_unit": null,
                            "unit": null
                        },
                        "staff": {
                            "base_price": "N/A",
                            "price_per_unit": null,
                            "unit": null
                        },
                        "guests": {
                            "base_price": "N/A",
                            "price_per_unit": null,
                            "unit": null
                        }
                    },
                    "ingredients": [
                        "1",
                        "2",
                        "Ei",
                        "Gl",
                        "GlW",
                        "Mi"
                    ],
                    "dish_type": "Vegetarisch"
                },
                {
                    "name": "Münchner Schnitzel mit Senf-Meerrettichkruste",
                    "prices": {
                        "students": {
                            "base_price": "N/A",
                            "price_per_unit": null,
                            "unit": null
                        },
                        "staff": {
                            "base_price": "N/A",
                            "price_per_unit": null,
                            "unit": null
                        },
                        "guests": {
                            "base_price": "N/A",
                            "price_per_unit": null,
                            "unit": null
                        }
                    },
                    "ingredients": [
                        "3",
                        "Ei",
                        "Gl",
                        "GlG",
                        "GlW",
                        "Kn",
                        "Mi",
                        "S",
                        "Sf",
                        "So"
                    ],
                    "dish_type": "Fleisch"
                }
            ]
        },
        {
            "date": "2021-05-12",
            "dishes": [
                {
                    "name": "Schinkennudeln (Vorderschinken) mit Zwiebeln und Ei",
                    "prices": {
                        "students": {
                            "base_price": "N/A",
                            "price_per_unit": null,
                            "unit": null
                        },
                        "staff": {
                            "base_price": "N/A",
                            "price_per_unit": null,
                            "unit": null
                        },
                        "guests": {
                            "base_price": "N/A",
                            "price_per_unit": null,
                            "unit": null
                        }
                    },
                    "ingredients": [
                        "2",
                        "3",
                        "8",
                        "Ei",
                        "Gl",
                        "GlW",
                        "Kn",
                        "Mi",
                        "S"
                    ],
                    "dish_type": "Pasta"
                },
                {
                    "name": "Frischer Schrobenhausener Spargel (g.g.A.) mit Putensteak und Sauce Hollandaise",
                    "prices": {
                        "students": {
                            "base_price": "N/A",
                            "price_per_unit": null,
                            "unit": null
                        },
                        "staff": {
                            "base_price": "N/A",
                            "price_per_unit": null,
                            "unit": null
                        },
                        "guests": {
                            "base_price": "N/A",
                            "price_per_unit": null,
                            "unit": null
                        }
                    },
                    "ingredients": [
                        "Ei",
                        "Mi",
                        "Sl"
                    ],
                    "dish_type": "Grill"
                },
                {
                    "name": "Buntes Gemüse in scharfer Kokosmilch",
                    "prices": {
                        "students": {
                            "base_price": "N/A",
                            "price_per_unit": null,
                            "unit": null
                        },
                        "staff": {
                            "base_price": "N/A",
                            "price_per_unit": null,
                            "unit": null
                        },
                        "guests": {
                            "base_price": "N/A",
                            "price_per_unit": null,
                            "unit": null
                        }
                    },
                    "ingredients": [
                        "2",
                        "Kn",
                        "Sf"
                    ],
                    "dish_type": "Vegan, Eintopf, Suppe"
                },
                {
                    "name": "Tagessuppe",
                    "prices": {
                        "students": {
                            "base_price": "N/A",
                            "price_per_unit": null,
                            "unit": null
                        },
                        "staff": {
                            "base_price": "N/A",
                            "price_per_unit": null,
                            "unit": null
                        },
                        "guests": {
                            "base_price": "N/A",
                            "price_per_unit": null,
                            "unit": null
                        }
                    },
                    "ingredients": [],
                    "dish_type": ""
                }
            ]
        },
        {
            "date": "2021-05-14",
            "dishes": [
                {
                    "name": "Gnocchi mit Pilzen, Tomaten und Spinat",
                    "prices": {
                        "students": {
                            "base_price": "N/A",
                            "price_per_unit": null,
                            "unit": null
                        },
                        "staff": {
                            "base_price": "N/A",
                            "price_per_unit": null,
                            "unit": null
                        },
                        "guests": {
                            "base_price": "N/A",
                            "price_per_unit": null,
                            "unit": null
                        }
                    },
                    "ingredients": [
                        "Gl",
                        "GlW",
                        "Kn"
                    ],
                    "dish_type": "Pasta"
                },
                {
                    "name": "Lachsfilet auf Blattspinat",
                    "prices": {
                        "students": {
                            "base_price": "N/A",
                            "price_per_unit": null,
                            "unit": null
                        },
                        "staff": {
                            "base_price": "N/A",
                            "price_per_unit": null,
                            "unit": null
                        },
                        "guests": {
                            "base_price": "N/A",
                            "price_per_unit": null,
                            "unit": null
                        }
                    },
                    "ingredients": [
                        "Fi",
                        "Gl",
                        "GlW",
                        "Kn",
                        "Mi"
                    ],
                    "dish_type": "Grill"
                },
                {
                    "name": "Italienischer Bohneneintopf",
                    "prices": {
                        "students": {
                            "base_price": "N/A",
                            "price_per_unit": null,
                            "unit": null
                        },
                        "staff": {
                            "base_price": "N/A",
                            "price_per_unit": null,
                            "unit": null
                        },
                        "guests": {
                            "base_price": "N/A",
                            "price_per_unit": null,
                            "unit": null
                        }
                    },
                    "ingredients": [
                        "Kn",
                        "Sl"
                    ],
                    "dish_type": "Vegan, Eintopf, Suppe"
                }
            ]
        }
    ]
}