{
    "number": 52,
    "year": 2020,
    "days": [
        {
            "date": "2020-12-21",
            "dishes": [
                {
                    "name": "Tagesgericht Fleisch oder Fisch",
                    "prices": {
                        "students": {
                            "base_price": 1.0,
                            "price_per_unit": 0.75,
                            "unit": "100g"
                        },
                        "staff": {
                            "base_price": 1.0,
                            "price_per_unit": 0.9,
                            "unit": "100g"
                        },
                        "guests": {
                            "base_price": 1.0,
                            "price_per_unit": 1.05,
                            "unit": "100g"
                        }
                    },
                    "ingredients": [],
                    "dish_type": "Self-Service"
                },
                {
                    "name": "Tagesgericht fleischlos / vegan",
                    "prices": {
                        "students": {
                            "base_price": "N/A",
                            "price_per_unit": null,
                            "unit": null
                        },
                        "staff": {
                            "base_price": "N/A",
                            "price_per_unit": null,
                            "unit": null
                        },
                        "guests": {
                            "base_price": "N/A",
                            "price_per_unit": null,
                            "unit": null
                        }
                    },
                    "ingredients": [],
                    "dish_type": ""
                },
                {
                    "name": "Tagesgemüse",
                    "prices": {
                        "students": {
                            "base_price": "N/A",
                            "price_per_unit": null,
                            "unit": null
                        },
                        "staff": {
                            "base_price": "N/A",
                            "price_per_unit": null,
                            "unit": null
                        },
                        "guests": {
                            "base_price": "N/A",
                            "price_per_unit": null,
                            "unit": null
                        }
                    },
                    "ingredients": [],
                    "dish_type": ""
                },
                {
                    "name": "Tagessuppe",
                    "prices": {
                        "students": {
                            "base_price": "N/A",
                            "price_per_unit": null,
                            "unit": null
                        },
                        "staff": {
                            "base_price": "N/A",
                            "price_per_unit": null,
                            "unit": null
                        },
                        "guests": {
                            "base_price": "N/A",
                            "price_per_unit": null,
                            "unit": null
                        }
                    },
                    "ingredients": [],
                    "dish_type": ""
                },
                {
                    "name": "Aktionsdessert",
                    "prices": {
                        "students": {
                            "base_price": "N/A",
                            "price_per_unit": null,
                            "unit": null
                        },
                        "staff": {
                            "base_price": "N/A",
                            "price_per_unit": null,
                            "unit": null
                        },
                        "guests": {
                            "base_price": "N/A",
                            "price_per_unit": null,
                            "unit": null
                        }
                    },
                    "ingredients": [],
                    "dish_type": "Dessert"
                }
            ]
        },
        {
            "date": "2020-12-22",
            "dishes": [
                {
                    "name": "Tagesgericht Fleisch / Fisch",
                    "prices": {
                        "students": {
                            "base_price": 1.0,
                            "price_per_unit": 0.75,
                            "unit": "100g"
                        },
                        "staff": {
                            "base_price": 1.0,
                            "price_per_unit": 0.9,
                            "unit": "100g"
                        },
                        "guests": {
                            "base_price": 1.0,
                            "price_per_unit": 1.05,
                            "unit": "100g"
                        }
                    },
                    "ingredients": [],
                    "dish_type": "Self-Service"
                },
                {
                    "name": "Tagesgericht fleischlos / vegan",
                    "prices": {
                        "students": {
                            "base_price": "N/A",
                            "price_per_unit": null,
                            "unit": null
                        },
                        "staff": {
                            "base_price": "N/A",
                            "price_per_unit": null,
                            "unit": null
                        },
                        "guests": {
                            "base_price": "N/A",
                            "price_per_unit": null,
                            "unit": null
                        }
                    },
                    "ingredients": [],
                    "dish_type": ""
                },
                {
                    "name": "Tagesgemüse",
                    "prices": {
                        "students": {
                            "base_price": "N/A",
                            "price_per_unit": null,
                            "unit": null
                        },
                        "staff": {
                            "base_price": "N/A",
                            "price_per_unit": null,
                            "unit": null
                        },
                        "guests": {
                            "base_price": "N/A",
                            "price_per_unit": null,
                            "unit": null
                        }
                    },
                    "ingredients": [],
                    "dish_type": ""
                },
                {
                    "name": "Tagessuppe",
                    "prices": {
                        "students": {
                            "base_price": "N/A",
                            "price_per_unit": null,
                            "unit": null
                        },
                        "staff": {
                            "base_price": "N/A",
                            "price_per_unit": null,
                            "unit": null
                        },
                        "guests": {
                            "base_price": "N/A",
                            "price_per_unit": null,
                            "unit": null
                        }
                    },
                    "ingredients": [],
                    "dish_type": ""
                },
                {
                    "name": "Aktionsdessert",
                    "prices": {
                        "students": {
                            "base_price": "N/A",
                            "price_per_unit": null,
                            "unit": null
                        },
                        "staff": {
                            "base_price": "N/A",
                            "price_per_unit": null,
                            "unit": null
                        },
                        "guests": {
                            "base_price": "N/A",
                            "price_per_unit": null,
                            "unit": null
                        }
                    },
                    "ingredients": [],
                    "dish_type": "Dessert"
                }
            ]
        },
        {
            "date": "2020-12-23",
            "dishes": [
                {
                    "name": "Tagesgericht Fleisch / Fisch",
                    "prices": {
                        "students": {
                            "base_price": 1.0,
                            "price_per_unit": 0.75,
                            "unit": "100g"
                        },
                        "staff": {
                            "base_price": 1.0,
                            "price_per_unit": 0.9,
                            "unit": "100g"
                        },
                        "guests": {
                            "base_price": 1.0,
                            "price_per_unit": 1.05,
                            "unit": "100g"
                        }
                    },
                    "ingredients": [],
                    "dish_type": "Self-Service"
                },
                {
                    "name": "Tagesgericht fleischlos / vegan",
                    "prices": {
                        "students": {
                            "base_price": "N/A",
                            "price_per_unit": null,
                            "unit": null
                        },
                        "staff": {
                            "base_price": "N/A",
                            "price_per_unit": null,
                            "unit": null
                        },
                        "guests": {
                            "base_price": "N/A",
                            "price_per_unit": null,
                            "unit": null
                        }
                    },
                    "ingredients": [],
                    "dish_type": ""
                },
                {
                    "name": "Tagesgemüse",
                    "prices": {
                        "students": {
                            "base_price": "N/A",
                            "price_per_unit": null,
                            "unit": null
                        },
                        "staff": {
                            "base_price": "N/A",
                            "price_per_unit": null,
                            "unit": null
                        },
                        "guests": {
                            "base_price": "N/A",
                            "price_per_unit": null,
                            "unit": null
                        }
                    },
                    "ingredients": [],
                    "dish_type": ""
                },
                {
                    "name": "Tagessuppe",
                    "prices": {
                        "students": {
                            "base_price": "N/A",
                            "price_per_unit": null,
                            "unit": null
                        },
                        "staff": {
                            "base_price": "N/A",
                            "price_per_unit": null,
                            "unit": null
                        },
                        "guests": {
                            "base_price": "N/A",
                            "price_per_unit": null,
                            "unit": null
                        }
                    },
                    "ingredients": [],
                    "dish_type": ""
                },
                {
                    "name": "Aktionsdessert",
                    "prices": {
                        "students": {
                            "base_price": "N/A",
                            "price_per_unit": null,
                            "unit": null
                        },
                        "staff": {
                            "base_price": "N/A",
                            "price_per_unit": null,
                            "unit": null
                        },
                        "guests": {
                            "base_price": "N/A",
                            "price_per_unit": null,
                            "unit": null
                        }
                    },
                    "ingredients": [],
                    "dish_type": "Dessert"
                }
            ]
        }
    ]
}