{
    "number": 40,
    "year": 2021,
    "days": [
        {
            "date": "2021-10-04",
            "dishes": [
                {
                    "name": "Pasta mit Tomatensauce",
                    "prices": {
                        "students": null,
                        "staff": null,
                        "guests": null
                    },
                    "ingredients": [
                        "Gl",
                        "GlW",
                        "Sl"
                    ],
                    "dish_type": "Pasta"
                },
                {
                    "name": "Putenrahmgeschnetzeltes mit Pasta und Kaisergemüse",
                    "prices": {
                        "students": null,
                        "staff": null,
                        "guests": null
                    },
                    "ingredients": [
                        "1",
                        "Gl",
                        "GlW",
                        "Mi"
                    ],
                    "dish_type": "Fleisch"
                }
            ]
        },
        {
            "date": "2021-10-05",
            "dishes": [
                {
                    "name": "Ofenkartoffel mit Tsatsiki",
                    "prices": {
                        "students": null,
                        "staff": null,
                        "guests": null
                    },
                    "ingredients": [
                        "14",
                        "Kn",
                        "Mi"
                    ],
                    "dish_type": "Vegetarisch"
                },
                {
                    "name": "Truthahnsteak mit Kartoffelsalat",
                    "prices": {
                        "students": null,
                        "staff": null,
                        "guests": null
                    },
                    "ingredients": [
                        "1",
                        "Kn",
                        "Sf"
                    ],
                    "dish_type": "Fleisch"
                }
            ]
        },
        {
            "date": "2021-10-06",
            "dishes": [
                {
                    "name": "Frühlingsrolle mit sweet Chillisauce und Reis",
                    "prices": {
                        "students": null,
                        "staff": null,
                        "guests": null
                    },
                    "ingredients": [
                        "Gl",
                        "GlW",
                        "Kn",
                        "Sl"
                    ],
                    "dish_type": "Vegetarisch"
                },
                {
                    "name": "Cheese Burger mit Wedges",
                    "prices": {
                        "students": null,
                        "staff": null,
                        "guests": null
                    },
                    "ingredients": [
                        "1",
                        "Ei",
                        "Gl",
                        "GlW",
                        "Mi",
                        "R",
                        "Sf"
                    ],
                    "dish_type": "Fleisch"
                }
            ]
        },
        {
            "date": "2021-10-07",
            "dishes": [
                {
                    "name": "Ravioli mit Pilzfüllung mit Pesto Genovese",
                    "prices": {
                        "students": null,
                        "staff": null,
                        "guests": null
                    },
                    "ingredients": [
                        "3",
                        "Ei",
                        "Gl",
                        "GlW",
                        "Kn",
                        "Mi",
                        "Sc",
                        "ScC",
                        "Sl"
                    ],
                    "dish_type": "Pasta"
                },
                {
                    "name": "Mediterrane Reispfanne mit Gemüse und Soja , dazu Sour-Ajvar-Dip",
                    "prices": {
                        "students": null,
                        "staff": null,
                        "guests": null
                    },
                    "ingredients": [
                        "Kn",
                        "Mi"
                    ],
                    "dish_type": "Vegetarisch"
                }
            ]
        },
        {
            "date": "2021-10-08",
            "dishes": [
                {
                    "name": "Wiener Würstchen mit Kartoffelsalat",
                    "prices": {
                        "students": null,
                        "staff": null,
                        "guests": null
                    },
                    "ingredients": [
                        "1",
                        "2",
                        "3",
                        "8",
                        "R",
                        "S",
                        "Sf"
                    ],
                    "dish_type": "Fleisch"
                },
                {
                    "name": "Weißwurst mit Kartoffelsalat",
                    "prices": {
                        "students": null,
                        "staff": null,
                        "guests": null
                    },
                    "ingredients": [
                        "1",
                        "8",
                        "R",
                        "S",
                        "Sf"
                    ],
                    "dish_type": ""
                },
                {
                    "name": "Debrecziner mit Kartoffelsalat",
                    "prices": {
                        "students": null,
                        "staff": null,
                        "guests": null
                    },
                    "ingredients": [
                        "1",
                        "2",
                        "3",
                        "8",
                        "R",
                        "S",
                        "Sf"
                    ],
                    "dish_type": ""
                },
                {
                    "name": "Kaiserschmarrn mit Apfelmus",
                    "prices": {
                        "students": null,
                        "staff": null,
                        "guests": null
                    },
                    "ingredients": [
                        "3",
                        "Ei",
                        "Gl",
                        "GlW",
                        "Mi"
                    ],
                    "dish_type": "Süßspeise"
                }
            ]
        }
    ],
    "version": "2.1"
}