{
    "canteen_id": "stubistro-goethestr",
    "weeks": [
        {
            "number": 40,
            "year": 2021,
            "days": [
                {
                    "date": "2021-10-04",
                    "dishes": [
                        {
                            "name": "Pasta mit Tomatensauce",
                            "prices": {
                                "students": {
                                    "base_price": "N/A",
                                    "price_per_unit": null,
                                    "unit": null
                                },
                                "staff": {
                                    "base_price": "N/A",
                                    "price_per_unit": null,
                                    "unit": null
                                },
                                "guests": {
                                    "base_price": "N/A",
                                    "price_per_unit": null,
                                    "unit": null
                                }
                            },
                            "ingredients": [
                                "Gl",
                                "GlW",
                                "Sl"
                            ],
                            "dish_type": "Pasta"
                        },
                        {
                            "name": "Putenrahmgeschnetzeltes mit Pasta und Kaisergemüse",
                            "prices": {
                                "students": {
                                    "base_price": "N/A",
                                    "price_per_unit": null,
                                    "unit": null
                                },
                                "staff": {
                                    "base_price": "N/A",
                                    "price_per_unit": null,
                                    "unit": null
                                },
                                "guests": {
                                    "base_price": "N/A",
                                    "price_per_unit": null,
                                    "unit": null
                                }
                            },
                            "ingredients": [
                                "1",
                                "Gl",
                                "GlW",
                                "Mi"
                            ],
                            "dish_type": "Fleisch"
                        }
                    ]
                },
                {
                    "date": "2021-10-05",
                    "dishes": [
                        {
                            "name": "Ofenkartoffel mit Tsatsiki",
                            "prices": {
                                "students": {
                                    "base_price": "N/A",
                                    "price_per_unit": null,
                                    "unit": null
                                },
                                "staff": {
                                    "base_price": "N/A",
                                    "price_per_unit": null,
                                    "unit": null
                                },
                                "guests": {
                                    "base_price": "N/A",
                                    "price_per_unit": null,
                                    "unit": null
                                }
                            },
                            "ingredients": [
                                "14",
                                "Kn",
                                "Mi"
                            ],
                            "dish_type": "Vegetarisch"
                        },
                        {
                            "name": "Truthahnsteak mit Kartoffelsalat",
                            "prices": {
                                "students": {
                                    "base_price": "N/A",
                                    "price_per_unit": null,
                                    "unit": null
                                },
                                "staff": {
                                    "base_price": "N/A",
                                    "price_per_unit": null,
                                    "unit": null
                                },
                                "guests": {
                                    "base_price": "N/A",
                                    "price_per_unit": null,
                                    "unit": null
                                }
                            },
                            "ingredients": [
                                "1",
                                "Kn",
                                "Sf"
                            ],
                            "dish_type": "Fleisch"
                        }
                    ]
                },
                {
                    "date": "2021-10-06",
                    "dishes": [
                        {
                            "name": "Frühlingsrolle mit sweet Chillisauce und Reis",
                            "prices": {
                                "students": {
                                    "base_price": "N/A",
                                    "price_per_unit": null,
                                    "unit": null
                                },
                                "staff": {
                                    "base_price": "N/A",
                                    "price_per_unit": null,
                                    "unit": null
                                },
                                "guests": {
                                    "base_price": "N/A",
                                    "price_per_unit": null,
                                    "unit": null
                                }
                            },
                            "ingredients": [
                                "Gl",
                                "GlW",
                                "Kn",
                                "Sl"
                            ],
                            "dish_type": "Vegetarisch"
                        },
                        {
                            "name": "Cheese Burger mit Wedges",
                            "prices": {
                                "students": {
                                    "base_price": "N/A",
                                    "price_per_unit": null,
                                    "unit": null
                                },
                                "staff": {
                                    "base_price": "N/A",
                                    "price_per_unit": null,
                                    "unit": null
                                },
                                "guests": {
                                    "base_price": "N/A",
                                    "price_per_unit": null,
                                    "unit": null
                                }
                            },
                            "ingredients": [
                                "1",
                                "Ei",
                                "Gl",
                                "GlW",
                                "Mi",
                                "R",
                                "Sf"
                            ],
                            "dish_type": "Fleisch"
                        }
                    ]
                },
                {
                    "date": "2021-10-07",
                    "dishes": [
                        {
                            "name": "Ravioli mit Pilzfüllung mit Pesto Genovese",
                            "prices": {
                                "students": {
                                    "base_price": "N/A",
                                    "price_per_unit": null,
                                    "unit": null
                                },
                                "staff": {
                                    "base_price": "N/A",
                                    "price_per_unit": null,
                                    "unit": null
                                },
                                "guests": {
                                    "base_price": "N/A",
                                    "price_per_unit": null,
                                    "unit": null
                                }
                            },
                            "ingredients": [
                                "3",
                                "Ei",
                                "Gl",
                                "GlW",
                                "Kn",
                                "Mi",
                                "Sc",
                                "ScC",
                                "Sl"
                            ],
                            "dish_type": "Pasta"
                        },
                        {
                            "name": "Mediterrane Reispfanne mit Gemüse und Soja , dazu Sour-Ajvar-Dip",
                            "prices": {
                                "students": {
                                    "base_price": "N/A",
                                    "price_per_unit": null,
                                    "unit": null
                                },
                                "staff": {
                                    "base_price": "N/A",
                                    "price_per_unit": null,
                                    "unit": null
                                },
                                "guests": {
                                    "base_price": "N/A",
                                    "price_per_unit": null,
                                    "unit": null
                                }
                            },
                            "ingredients": [
                                "Kn",
                                "Mi"
                            ],
                            "dish_type": "Vegetarisch"
                        }
                    ]
                },
                {
                    "date": "2021-10-08",
                    "dishes": [
                        {
                            "name": "Wiener Würstchen mit Kartoffelsalat",
                            "prices": {
                                "students": {
                                    "base_price": "N/A",
                                    "price_per_unit": null,
                                    "unit": null
                                },
                                "staff": {
                                    "base_price": "N/A",
                                    "price_per_unit": null,
                                    "unit": null
                                },
                                "guests": {
                                    "base_price": "N/A",
                                    "price_per_unit": null,
                                    "unit": null
                                }
                            },
                            "ingredients": [
                                "1",
                                "2",
                                "3",
                                "8",
                                "R",
                                "S",
                                "Sf"
                            ],
                            "dish_type": "Fleisch"
                        },
                        {
                            "name": "Weißwurst mit Kartoffelsalat",
                            "prices": {
                                "students": {
                                    "base_price": "N/A",
                                    "price_per_unit": null,
                                    "unit": null
                                },
                                "staff": {
                                    "base_price": "N/A",
                                    "price_per_unit": null,
                                    "unit": null
                                },
                                "guests": {
                                    "base_price": "N/A",
                                    "price_per_unit": null,
                                    "unit": null
                                }
                            },
                            "ingredients": [
                                "1",
                                "8",
                                "R",
                                "S",
                                "Sf"
                            ],
                            "dish_type": ""
                        },
                        {
                            "name": "Debrecziner mit Kartoffelsalat",
                            "prices": {
                                "students": {
                                    "base_price": "N/A",
                                    "price_per_unit": null,
                                    "unit": null
                                },
                                "staff": {
                                    "base_price": "N/A",
                                    "price_per_unit": null,
                                    "unit": null
                                },
                                "guests": {
                                    "base_price": "N/A",
                                    "price_per_unit": null,
                                    "unit": null
                                }
                            },
                            "ingredients": [
                                "1",
                                "2",
                                "3",
                                "8",
                                "R",
                                "S",
                                "Sf"
                            ],
                            "dish_type": ""
                        },
                        {
                            "name": "Kaiserschmarrn mit Apfelmus",
                            "prices": {
                                "students": {
                                    "base_price": "N/A",
                                    "price_per_unit": null,
                                    "unit": null
                                },
                                "staff": {
                                    "base_price": "N/A",
                                    "price_per_unit": null,
                                    "unit": null
                                },
                                "guests": {
                                    "base_price": "N/A",
                                    "price_per_unit": null,
                                    "unit": null
                                }
                            },
                            "ingredients": [
                                "3",
                                "Ei",
                                "Gl",
                                "GlW",
                                "Mi"
                            ],
                            "dish_type": "Süßspeise"
                        }
                    ]
                }
            ]
        },
        {
            "number": 41,
            "year": 2021,
            "days": [
                {
                    "date": "2021-10-11",
                    "dishes": [
                        {
                            "name": "Käsespätzle mit Röstzwiebeln",
                            "prices": {
                                "students": {
                                    "base_price": "N/A",
                                    "price_per_unit": null,
                                    "unit": null
                                },
                                "staff": {
                                    "base_price": "N/A",
                                    "price_per_unit": null,
                                    "unit": null
                                },
                                "guests": {
                                    "base_price": "N/A",
                                    "price_per_unit": null,
                                    "unit": null
                                }
                            },
                            "ingredients": [
                                "1",
                                "Ei",
                                "Gl",
                                "GlD",
                                "GlW",
                                "Mi"
                            ],
                            "dish_type": "Pasta"
                        },
                        {
                            "name": "Rindergeschnetzeltes mit Knöpfle",
                            "prices": {
                                "students": {
                                    "base_price": "N/A",
                                    "price_per_unit": null,
                                    "unit": null
                                },
                                "staff": {
                                    "base_price": "N/A",
                                    "price_per_unit": null,
                                    "unit": null
                                },
                                "guests": {
                                    "base_price": "N/A",
                                    "price_per_unit": null,
                                    "unit": null
                                }
                            },
                            "ingredients": [
                                "Ei",
                                "Gl",
                                "GlD",
                                "GlW",
                                "R"
                            ],
                            "dish_type": "Fleisch"
                        }
                    ]
                },
                {
                    "date": "2021-10-12",
                    "dishes": [
                        {
                            "name": "Pasta Karotte-Zucchini in Olivenöl , dazu Hartkäse",
                            "prices": {
                                "students": {
                                    "base_price": "N/A",
                                    "price_per_unit": null,
                                    "unit": null
                                },
                                "staff": {
                                    "base_price": "N/A",
                                    "price_per_unit": null,
                                    "unit": null
                                },
                                "guests": {
                                    "base_price": "N/A",
                                    "price_per_unit": null,
                                    "unit": null
                                }
                            },
                            "ingredients": [
                                "Gl",
                                "GlW"
                            ],
                            "dish_type": "Pasta"
                        },
                        {
                            "name": "Currywurst mit Curryketchup in der Semmel",
                            "prices": {
                                "students": {
                                    "base_price": "N/A",
                                    "price_per_unit": null,
                                    "unit": null
                                },
                                "staff": {
                                    "base_price": "N/A",
                                    "price_per_unit": null,
                                    "unit": null
                                },
                                "guests": {
                                    "base_price": "N/A",
                                    "price_per_unit": null,
                                    "unit": null
                                }
                            },
                            "ingredients": [
                                "2",
                                "3",
                                "8",
                                "Gl",
                                "GlG",
                                "GlR",
                                "GlW",
                                "R",
                                "S",
                                "Sf",
                                "Sl"
                            ],
                            "dish_type": "Fleisch"
                        }
                    ]
                },
                {
                    "date": "2021-10-13",
                    "dishes": [
                        {
                            "name": "Gratiniertes Ofengemüse mit Tomatensauce",
                            "prices": {
                                "students": {
                                    "base_price": "N/A",
                                    "price_per_unit": null,
                                    "unit": null
                                },
                                "staff": {
                                    "base_price": "N/A",
                                    "price_per_unit": null,
                                    "unit": null
                                },
                                "guests": {
                                    "base_price": "N/A",
                                    "price_per_unit": null,
                                    "unit": null
                                }
                            },
                            "ingredients": [
                                "Sl"
                            ],
                            "dish_type": "Vegetarisch"
                        },
                        {
                            "name": "Cordon bleu (Vorderschinken) mit Kartoffel-Gurken-Salat",
                            "prices": {
                                "students": {
                                    "base_price": "N/A",
                                    "price_per_unit": null,
                                    "unit": null
                                },
                                "staff": {
                                    "base_price": "N/A",
                                    "price_per_unit": null,
                                    "unit": null
                                },
                                "guests": {
                                    "base_price": "N/A",
                                    "price_per_unit": null,
                                    "unit": null
                                }
                            },
                            "ingredients": [
                                "1",
                                "2",
                                "3",
                                "Gl",
                                "GlW",
                                "Mi",
                                "S",
                                "Sf"
                            ],
                            "dish_type": "Fleisch"
                        }
                    ]
                },
                {
                    "date": "2021-10-14",
                    "dishes": [
                        {
                            "name": "Tortellini mit Käsefüllung in Tomatensauce",
                            "prices": {
                                "students": {
                                    "base_price": "N/A",
                                    "price_per_unit": null,
                                    "unit": null
                                },
                                "staff": {
                                    "base_price": "N/A",
                                    "price_per_unit": null,
                                    "unit": null
                                },
                                "guests": {
                                    "base_price": "N/A",
                                    "price_per_unit": null,
                                    "unit": null
                                }
                            },
                            "ingredients": [
                                "Ei",
                                "Gl",
                                "GlW",
                                "Mi",
                                "Sl"
                            ],
                            "dish_type": "Pasta"
                        },
                        {
                            "name": "Patros-Pfanne mit mediterranem Gemüse, frittierten Kartoffeln und Käse",
                            "prices": {
                                "students": {
                                    "base_price": "N/A",
                                    "price_per_unit": null,
                                    "unit": null
                                },
                                "staff": {
                                    "base_price": "N/A",
                                    "price_per_unit": null,
                                    "unit": null
                                },
                                "guests": {
                                    "base_price": "N/A",
                                    "price_per_unit": null,
                                    "unit": null
                                }
                            },
                            "ingredients": [
                                "Mi"
                            ],
                            "dish_type": "Vegetarisch"
                        }
                    ]
                },
                {
                    "date": "2021-10-15",
                    "dishes": [
                        {
                            "name": "Kartoffelgratin mit Rataouille",
                            "prices": {
                                "students": {
                                    "base_price": "N/A",
                                    "price_per_unit": null,
                                    "unit": null
                                },
                                "staff": {
                                    "base_price": "N/A",
                                    "price_per_unit": null,
                                    "unit": null
                                },
                                "guests": {
                                    "base_price": "N/A",
                                    "price_per_unit": null,
                                    "unit": null
                                }
                            },
                            "ingredients": [
                                "Ei",
                                "Kn",
                                "Mi"
                            ],
                            "dish_type": "Vegetarisch"
                        },
                        {
                            "name": "Fish & Chips mit Remouladensauce",
                            "prices": {
                                "students": {
                                    "base_price": "N/A",
                                    "price_per_unit": null,
                                    "unit": null
                                },
                                "staff": {
                                    "base_price": "N/A",
                                    "price_per_unit": null,
                                    "unit": null
                                },
                                "guests": {
                                    "base_price": "N/A",
                                    "price_per_unit": null,
                                    "unit": null
                                }
                            },
                            "ingredients": [
                                "1",
                                "11",
                                "5",
                                "Ei",
                                "Fi",
                                "Gl",
                                "GlW",
                                "Mi",
                                "Sf",
                                "Sw"
                            ],
                            "dish_type": "Fisch"
                        }
                    ]
                }
            ]
        },
        {
            "number": 42,
            "year": 2021,
            "days": [
                {
                    "date": "2021-10-18",
                    "dishes": [
                        {
                            "name": "Pizzaecke Verdura mit Mozzarella und Gemüse",
                            "prices": {
                                "students": {
                                    "base_price": "N/A",
                                    "price_per_unit": null,
                                    "unit": null
                                },
                                "staff": {
                                    "base_price": "N/A",
                                    "price_per_unit": null,
                                    "unit": null
                                },
                                "guests": {
                                    "base_price": "N/A",
                                    "price_per_unit": null,
                                    "unit": null
                                }
                            },
                            "ingredients": [
                                "Gl",
                                "GlW",
                                "Kn",
                                "Mi",
                                "Sl"
                            ],
                            "dish_type": "Pizza"
                        },
                        {
                            "name": "Pizzaecke Speciale - mit Peperonisalami, Hinterschinken und Champignons",
                            "prices": {
                                "students": {
                                    "base_price": "N/A",
                                    "price_per_unit": null,
                                    "unit": null
                                },
                                "staff": {
                                    "base_price": "N/A",
                                    "price_per_unit": null,
                                    "unit": null
                                },
                                "guests": {
                                    "base_price": "N/A",
                                    "price_per_unit": null,
                                    "unit": null
                                }
                            },
                            "ingredients": [
                                "2",
                                "3",
                                "Gl",
                                "GlW",
                                "Mi",
                                "S",
                                "Sf"
                            ],
                            "dish_type": ""
                        },
                        {
                            "name": "Gnocchi mit Tomaten, Oliven und Weißkäse",
                            "prices": {
                                "students": {
                                    "base_price": "N/A",
                                    "price_per_unit": null,
                                    "unit": null
                                },
                                "staff": {
                                    "base_price": "N/A",
                                    "price_per_unit": null,
                                    "unit": null
                                },
                                "guests": {
                                    "base_price": "N/A",
                                    "price_per_unit": null,
                                    "unit": null
                                }
                            },
                            "ingredients": [
                                "6",
                                "Gl",
                                "GlW",
                                "Mi"
                            ],
                            "dish_type": "Vegetarisch"
                        }
                    ]
                },
                {
                    "date": "2021-10-19",
                    "dishes": [
                        {
                            "name": "Spinatknödel mit zerlassener Butter, Salbei und Hartkäse",
                            "prices": {
                                "students": {
                                    "base_price": "N/A",
                                    "price_per_unit": null,
                                    "unit": null
                                },
                                "staff": {
                                    "base_price": "N/A",
                                    "price_per_unit": null,
                                    "unit": null
                                },
                                "guests": {
                                    "base_price": "N/A",
                                    "price_per_unit": null,
                                    "unit": null
                                }
                            },
                            "ingredients": [
                                "2",
                                "Ei",
                                "Gl",
                                "GlW",
                                "Mi",
                                "Sl"
                            ],
                            "dish_type": "Vegetarisch"
                        },
                        {
                            "name": "Fleischpflanzerl mit mediterranem Kartoffelsalat",
                            "prices": {
                                "students": {
                                    "base_price": "N/A",
                                    "price_per_unit": null,
                                    "unit": null
                                },
                                "staff": {
                                    "base_price": "N/A",
                                    "price_per_unit": null,
                                    "unit": null
                                },
                                "guests": {
                                    "base_price": "N/A",
                                    "price_per_unit": null,
                                    "unit": null
                                }
                            },
                            "ingredients": [
                                "2",
                                "Ei",
                                "Gl",
                                "GlW",
                                "R",
                                "S",
                                "Sf",
                                "Sl"
                            ],
                            "dish_type": "Fleisch"
                        }
                    ]
                },
                {
                    "date": "2021-10-20",
                    "dishes": [
                        {
                            "name": "Pilz-Ravioli mit Olivenöl, Kirschtomaten, Rucola und Grana Padano",
                            "prices": {
                                "students": {
                                    "base_price": "N/A",
                                    "price_per_unit": null,
                                    "unit": null
                                },
                                "staff": {
                                    "base_price": "N/A",
                                    "price_per_unit": null,
                                    "unit": null
                                },
                                "guests": {
                                    "base_price": "N/A",
                                    "price_per_unit": null,
                                    "unit": null
                                }
                            },
                            "ingredients": [
                                "2",
                                "Ei",
                                "Gl",
                                "GlW",
                                "Mi",
                                "Sl"
                            ],
                            "dish_type": "Pasta"
                        },
                        {
                            "name": "Süßkartoffelpommes aus dem Ofen mit veganem Guacamoledip",
                            "prices": {
                                "students": {
                                    "base_price": "N/A",
                                    "price_per_unit": null,
                                    "unit": null
                                },
                                "staff": {
                                    "base_price": "N/A",
                                    "price_per_unit": null,
                                    "unit": null
                                },
                                "guests": {
                                    "base_price": "N/A",
                                    "price_per_unit": null,
                                    "unit": null
                                }
                            },
                            "ingredients": [
                                "3",
                                "Kn",
                                "So"
                            ],
                            "dish_type": "Vegetarisch"
                        }
                    ]
                },
                {
                    "date": "2021-10-21",
                    "dishes": [
                        {
                            "name": "Bami Goreng mit Gemüse und Hähnchenbrustfleisch",
                            "prices": {
                                "students": {
                                    "base_price": "N/A",
                                    "price_per_unit": null,
                                    "unit": null
                                },
                                "staff": {
                                    "base_price": "N/A",
                                    "price_per_unit": null,
                                    "unit": null
                                },
                                "guests": {
                                    "base_price": "N/A",
                                    "price_per_unit": null,
                                    "unit": null
                                }
                            },
                            "ingredients": [
                                "Ei",
                                "Gl",
                                "GlW",
                                "Kn",
                                "So"
                            ],
                            "dish_type": "Wok"
                        }
                    ]
                },
                {
                    "date": "2021-10-22",
                    "dishes": [
                        {
                            "name": "Backfisch (MSC) mit Kartoffelsalat",
                            "prices": {
                                "students": {
                                    "base_price": "N/A",
                                    "price_per_unit": null,
                                    "unit": null
                                },
                                "staff": {
                                    "base_price": "N/A",
                                    "price_per_unit": null,
                                    "unit": null
                                },
                                "guests": {
                                    "base_price": "N/A",
                                    "price_per_unit": null,
                                    "unit": null
                                }
                            },
                            "ingredients": [
                                "1",
                                "Fi",
                                "Gl",
                                "GlW",
                                "Sf"
                            ],
                            "dish_type": "Fisch"
                        },
                        {
                            "name": "Apfelstrudel mit Vanillesauce",
                            "prices": {
                                "students": {
                                    "base_price": "N/A",
                                    "price_per_unit": null,
                                    "unit": null
                                },
                                "staff": {
                                    "base_price": "N/A",
                                    "price_per_unit": null,
                                    "unit": null
                                },
                                "guests": {
                                    "base_price": "N/A",
                                    "price_per_unit": null,
                                    "unit": null
                                }
                            },
                            "ingredients": [
                                "Ei",
                                "Gl",
                                "GlW",
                                "Mi"
                            ],
                            "dish_type": "Süßspeise"
                        }
                    ]
                }
            ]
        },
        {
            "number": 43,
            "year": 2021,
            "days": [
                {
                    "date": "2021-10-25",
                    "dishes": [
                        {
                            "name": "Gefüllte Paprikaschotenhälfte mit Tomatensauce , dazu Reis",
                            "prices": {
                                "students": {
                                    "base_price": "N/A",
                                    "price_per_unit": null,
                                    "unit": null
                                },
                                "staff": {
                                    "base_price": "N/A",
                                    "price_per_unit": null,
                                    "unit": null
                                },
                                "guests": {
                                    "base_price": "N/A",
                                    "price_per_unit": null,
                                    "unit": null
                                }
                            },
                            "ingredients": [
                                "2",
                                "Gl",
                                "GlD",
                                "Kn",
                                "Mi",
                                "Sl"
                            ],
                            "dish_type": "Vegetarisch"
                        },
                        {
                            "name": "Paniertes Hähnchenschnitzel mit Wedges",
                            "prices": {
                                "students": {
                                    "base_price": "N/A",
                                    "price_per_unit": null,
                                    "unit": null
                                },
                                "staff": {
                                    "base_price": "N/A",
                                    "price_per_unit": null,
                                    "unit": null
                                },
                                "guests": {
                                    "base_price": "N/A",
                                    "price_per_unit": null,
                                    "unit": null
                                }
                            },
                            "ingredients": [
                                "Ei",
                                "Gl",
                                "GlW"
                            ],
                            "dish_type": "Fleisch"
                        }
                    ]
                },
                {
                    "date": "2021-10-26",
                    "dishes": [
                        {
                            "name": "Gemüsemaultaschen mit Tomatensauce",
                            "prices": {
                                "students": {
                                    "base_price": "N/A",
                                    "price_per_unit": null,
                                    "unit": null
                                },
                                "staff": {
                                    "base_price": "N/A",
                                    "price_per_unit": null,
                                    "unit": null
                                },
                                "guests": {
                                    "base_price": "N/A",
                                    "price_per_unit": null,
                                    "unit": null
                                }
                            },
                            "ingredients": [],
                            "dish_type": "Pasta"
                        },
                        {
                            "name": "Pasta mit Bolognese-Sauce",
                            "prices": {
                                "students": {
                                    "base_price": "N/A",
                                    "price_per_unit": null,
                                    "unit": null
                                },
                                "staff": {
                                    "base_price": "N/A",
                                    "price_per_unit": null,
                                    "unit": null
                                },
                                "guests": {
                                    "base_price": "N/A",
                                    "price_per_unit": null,
                                    "unit": null
                                }
                            },
                            "ingredients": [
                                "99",
                                "Gl",
                                "GlW",
                                "Kn",
                                "Mi",
                                "R",
                                "Sl"
                            ],
                            "dish_type": "Fleisch"
                        }
                    ]
                },
                {
                    "date": "2021-10-27",
                    "dishes": [
                        {
                            "name": "Senner Rösti mit Tomate und Käse überbacken , dazu Pesto Genovese",
                            "prices": {
                                "students": {
                                    "base_price": "N/A",
                                    "price_per_unit": null,
                                    "unit": null
                                },
                                "staff": {
                                    "base_price": "N/A",
                                    "price_per_unit": null,
                                    "unit": null
                                },
                                "guests": {
                                    "base_price": "N/A",
                                    "price_per_unit": null,
                                    "unit": null
                                }
                            },
                            "ingredients": [
                                "3",
                                "Ei",
                                "Kn",
                                "Mi",
                                "Sc",
                                "ScC"
                            ],
                            "dish_type": "Vegetarisch"
                        },
                        {
                            "name": "Frisch aufgebackener Leberkäse mit Kartoffelsalat",
                            "prices": {
                                "students": {
                                    "base_price": "N/A",
                                    "price_per_unit": null,
                                    "unit": null
                                },
                                "staff": {
                                    "base_price": "N/A",
                                    "price_per_unit": null,
                                    "unit": null
                                },
                                "guests": {
                                    "base_price": "N/A",
                                    "price_per_unit": null,
                                    "unit": null
                                }
                            },
                            "ingredients": [
                                "2",
                                "3",
                                "8",
                                "R",
                                "S",
                                "Sl"
                            ],
                            "dish_type": "Fleisch"
                        }
                    ]
                },
                {
                    "date": "2021-10-28",
                    "dishes": [
                        {
                            "name": "Reispfanne Paella-Art mit Gemüse und Soja",
                            "prices": {
                                "students": {
                                    "base_price": "N/A",
                                    "price_per_unit": null,
                                    "unit": null
                                },
                                "staff": {
                                    "base_price": "N/A",
                                    "price_per_unit": null,
                                    "unit": null
                                },
                                "guests": {
                                    "base_price": "N/A",
                                    "price_per_unit": null,
                                    "unit": null
                                }
                            },
                            "ingredients": [
                                "Kn",
                                "Sl",
                                "So"
                            ],
                            "dish_type": "Vegetarisch"
                        },
                        {
                            "name": "Crunchy Chicken* Burger mit Käse",
                            "prices": {
                                "students": {
                                    "base_price": "N/A",
                                    "price_per_unit": null,
                                    "unit": null
                                },
                                "staff": {
                                    "base_price": "N/A",
                                    "price_per_unit": null,
                                    "unit": null
                                },
                                "guests": {
                                    "base_price": "N/A",
                                    "price_per_unit": null,
                                    "unit": null
                                }
                            },
                            "ingredients": [
                                "1",
                                "Ei",
                                "Gl",
                                "GlG",
                                "GlW",
                                "Mi",
                                "Se",
                                "Sf",
                                "Sl"
                            ],
                            "dish_type": "Fleisch"
                        }
                    ]
                },
                {
                    "date": "2021-10-29",
                    "dishes": [
                        {
                            "name": "Hot Dog mit Röstzwiebeln, Gurke und Jalapenos",
                            "prices": {
                                "students": {
                                    "base_price": "N/A",
                                    "price_per_unit": null,
                                    "unit": null
                                },
                                "staff": {
                                    "base_price": "N/A",
                                    "price_per_unit": null,
                                    "unit": null
                                },
                                "guests": {
                                    "base_price": "N/A",
                                    "price_per_unit": null,
                                    "unit": null
                                }
                            },
                            "ingredients": [
                                "1",
                                "2",
                                "3",
                                "8",
                                "9",
                                "Ei",
                                "Gl",
                                "GlW",
                                "R",
                                "S",
                                "Sf"
                            ],
                            "dish_type": "Fleisch"
                        },
                        {
                            "name": "Topfenstrudel mit Birnen und Rosinen, dazu Zwetschgenröstern",
                            "prices": {
                                "students": {
                                    "base_price": "N/A",
                                    "price_per_unit": null,
                                    "unit": null
                                },
                                "staff": {
                                    "base_price": "N/A",
                                    "price_per_unit": null,
                                    "unit": null
                                },
                                "guests": {
                                    "base_price": "N/A",
                                    "price_per_unit": null,
                                    "unit": null
                                }
                            },
                            "ingredients": [
                                "Ei",
                                "Gl",
                                "GlW",
                                "Mi"
                            ],
                            "dish_type": "Süßspeise"
                        }
                    ]
                }
            ]
        }
    ]
}