{
    "number": 38,
    "year": 2020,
    "days": [
        {
            "date": "2020-09-14",
            "dishes": [
                {
                    "name": "Mexikanischer Reistopf mit Bohnen, Paprika und Mais",
                    "prices": {
                        "students": {
                            "base_price": "N/A",
                            "price_per_unit": null,
                            "unit": null
                        },
                        "staff": {
                            "base_price": "N/A",
                            "price_per_unit": null,
                            "unit": null
                        },
                        "guests": {
                            "base_price": "N/A",
                            "price_per_unit": null,
                            "unit": null
                        }
                    },
                    "ingredients": [
                        "Kn"
                    ],
                    "dish_type": "Tellergericht Vegan"
                },
                {
                    "name": "Cordon bleu vom Schwein (mit Formfleisch-Kochschinken) mit Countrykartoffel, Erbsen und Karotten",
                    "prices": {
                        "students": {
                            "base_price": "N/A",
                            "price_per_unit": null,
                            "unit": null
                        },
                        "staff": {
                            "base_price": "N/A",
                            "price_per_unit": null,
                            "unit": null
                        },
                        "guests": {
                            "base_price": "N/A",
                            "price_per_unit": null,
                            "unit": null
                        }
                    },
                    "ingredients": [
                        "2",
                        "3",
                        "8",
                        "Gl",
                        "GlG",
                        "GlW",
                        "Kn",
                        "Mi",
                        "S",
                        "Sf",
                        "Sl"
                    ],
                    "dish_type": "Tellergericht Fleisch"
                }
            ]
        },
        {
            "date": "2020-09-15",
            "dishes": [
                {
                    "name": "Nasi Goreng (mit Hähnchenfleisch)",
                    "prices": {
                        "students": {
                            "base_price": "N/A",
                            "price_per_unit": null,
                            "unit": null
                        },
                        "staff": {
                            "base_price": "N/A",
                            "price_per_unit": null,
                            "unit": null
                        },
                        "guests": {
                            "base_price": "N/A",
                            "price_per_unit": null,
                            "unit": null
                        }
                    },
                    "ingredients": [
                        "2",
                        "Gl",
                        "GlW",
                        "Kn",
                        "Sf",
                        "So"
                    ],
                    "dish_type": "Tellergericht Wok"
                },
                {
                    "name": "Linseneintopf mit Gemüse",
                    "prices": {
                        "students": {
                            "base_price": "N/A",
                            "price_per_unit": null,
                            "unit": null
                        },
                        "staff": {
                            "base_price": "N/A",
                            "price_per_unit": null,
                            "unit": null
                        },
                        "guests": {
                            "base_price": "N/A",
                            "price_per_unit": null,
                            "unit": null
                        }
                    },
                    "ingredients": [
                        "3",
                        "5",
                        "Sl",
                        "Sw"
                    ],
                    "dish_type": "Tellergericht Vegan"
                }
            ]
        },
        {
            "date": "2020-09-16",
            "dishes": [
                {
                    "name": "Nürnberger Würstchen mit Kartoffelbrei und Sauerkraut",
                    "prices": {
                        "students": {
                            "base_price": "N/A",
                            "price_per_unit": null,
                            "unit": null
                        },
                        "staff": {
                            "base_price": "N/A",
                            "price_per_unit": null,
                            "unit": null
                        },
                        "guests": {
                            "base_price": "N/A",
                            "price_per_unit": null,
                            "unit": null
                        }
                    },
                    "ingredients": [
                        "3",
                        "8",
                        "Mi",
                        "R",
                        "S"
                    ],
                    "dish_type": "Tellergericht Grill"
                },
                {
                    "name": "Asiatische Reis-Gemüsepfanne",
                    "prices": {
                        "students": {
                            "base_price": "N/A",
                            "price_per_unit": null,
                            "unit": null
                        },
                        "staff": {
                            "base_price": "N/A",
                            "price_per_unit": null,
                            "unit": null
                        },
                        "guests": {
                            "base_price": "N/A",
                            "price_per_unit": null,
                            "unit": null
                        }
                    },
                    "ingredients": [
                        "2",
                        "Kn",
                        "Sf",
                        "Sl",
                        "So"
                    ],
                    "dish_type": "Tellergericht Vegan"
                }
            ]
        },
        {
            "date": "2020-09-17",
            "dishes": [
                {
                    "name": "Fleischpflanzerl mit Rahmsauce, Kartoffelbrei, Erbsen",
                    "prices": {
                        "students": {
                            "base_price": "N/A",
                            "price_per_unit": null,
                            "unit": null
                        },
                        "staff": {
                            "base_price": "N/A",
                            "price_per_unit": null,
                            "unit": null
                        },
                        "guests": {
                            "base_price": "N/A",
                            "price_per_unit": null,
                            "unit": null
                        }
                    },
                    "ingredients": [
                        "Ei",
                        "Gl",
                        "GlG",
                        "GlW",
                        "Kn",
                        "Mi",
                        "R",
                        "S"
                    ],
                    "dish_type": "Tellergericht Grill"
                },
                {
                    "name": "Couscous mit Pilzen, Tomaten und Spinat",
                    "prices": {
                        "students": {
                            "base_price": "N/A",
                            "price_per_unit": null,
                            "unit": null
                        },
                        "staff": {
                            "base_price": "N/A",
                            "price_per_unit": null,
                            "unit": null
                        },
                        "guests": {
                            "base_price": "N/A",
                            "price_per_unit": null,
                            "unit": null
                        }
                    },
                    "ingredients": [
                        "Gl",
                        "GlW",
                        "Kn",
                        "So"
                    ],
                    "dish_type": "Tellergericht Vegan"
                }
            ]
        },
        {
            "date": "2020-09-18",
            "dishes": [
                {
                    "name": "Rindergeschnetzeltes (GQB) mit grünem Pfeffer, Reis und Mischgemüse",
                    "prices": {
                        "students": {
                            "base_price": "N/A",
                            "price_per_unit": null,
                            "unit": null
                        },
                        "staff": {
                            "base_price": "N/A",
                            "price_per_unit": null,
                            "unit": null
                        },
                        "guests": {
                            "base_price": "N/A",
                            "price_per_unit": null,
                            "unit": null
                        }
                    },
                    "ingredients": [
                        "Gl",
                        "GlG",
                        "GlW",
                        "Kn",
                        "Mi",
                        "R"
                    ],
                    "dish_type": "Tellergericht Grill"
                }
            ]
        }
    ]
}